poetrify/__init__.py
poetrify/api.py
poetrify/cli.py
poetrify/commands.py
poetrify/files.py
poetrify/http.py
poetrify/packages.py
poetrify-0.4.2.dist-info/entry_points.txt
poetrify-0.4.2.dist-info/LICENSE
poetrify-0.4.2.dist-info/WHEEL
poetrify-0.4.2.dist-info/METADATA
poetrify-0.4.2.dist-info/RECORD
